Metadata-Version: 2.1
Name: efb-wechat-slave
Version: 2.0.7
Summary: WeChat Slave Channel for EH Forwarder Bot, based on WeChat Web API.
Home-page: https://ews.1a23.studio
Author: Eana Hufwe
Author-email: ilove@1a23.com
License: AGPLv3+
Keywords: ehforwarderbot,EH Forwarder Bot,EH Forwarder Bot Slave Channel,wechat,weixin,chatbot
Platform: UNKNOWN
Classifier: Development Status :: 3 - Alpha
Classifier: License :: OSI Approved :: GNU Affero General Public License v3 or later (AGPLv3+)
Classifier: Intended Audience :: Developers
Classifier: Intended Audience :: End Users/Desktop
Classifier: Programming Language :: Python :: 3 :: Only
Classifier: Programming Language :: Python :: 3.6
Classifier: Programming Language :: Python :: 3.7
Classifier: Topic :: Communications :: Chat
Classifier: Topic :: Utilities
Requires-Python: >=3.6
Requires-Dist: ehforwarderbot (>=2.0.0)
Requires-Dist: python-magic
Requires-Dist: pillow
Requires-Dist: pyqrcode
Requires-Dist: pypng
Requires-Dist: PyYaml (>=5.3)
Requires-Dist: requests (>=2.22.0)
Requires-Dist: typing-extensions
Requires-Dist: bullet
Requires-Dist: cjkwrap
Provides-Extra: tests
Requires-Dist: pytest ; extra == 'tests'
Requires-Dist: mypy ; extra == 'tests'
